README.md
setup.py
pulumi_runner/__init__.py
pulumi_runner/_utilities.py
pulumi_runner/provider.py
pulumi_runner/pulumi-plugin.json
pulumi_runner/py.typed
pulumi_runner.egg-info/PKG-INFO
pulumi_runner.egg-info/SOURCES.txt
pulumi_runner.egg-info/dependency_links.txt
pulumi_runner.egg-info/not-zip-safe
pulumi_runner.egg-info/requires.txt
pulumi_runner.egg-info/top_level.txt
pulumi_runner/deb/__init__.py
pulumi_runner/deb/_inputs.py
pulumi_runner/deb/outputs.py
pulumi_runner/runner/__init__.py
pulumi_runner/runner/_inputs.py
pulumi_runner/runner/local_file.py
pulumi_runner/runner/outputs.py
pulumi_runner/runner/ssh_deployer.py
pulumi_runner/runner/string_file.py
pulumi_runner/ssh/__init__.py
pulumi_runner/ssh/_inputs.py
pulumi_runner/ssh/outputs.py